SPARTACUS/__init__.py
SPARTACUS/spartacus.py
SPARTACUS/spatial_silhouette.py
SPARTACUS/tests/R_labels_matrixA.csv
SPARTACUS/tests/SPARTACUS_comparison_with_R_function.R
SPARTACUS/tests/__init__.py
SPARTACUS/tests/list_neighbors.csv
SPARTACUS/tests/matrixA.csv
SPARTACUS/tests/random_data.csv
SPARTACUS/tests/random_data_spatial.csv
SPARTACUS/tests/random_labels.csv
SPARTACUS/tests/test_spartacus.py
SPARTACUS/tests/test_spatial_silhouette.py
SPARTACUS10/__init__.py
SPARTACUS10/spartacus.py
SPARTACUS10/spatial_silhouette.py
SPARTACUS10/tests/R_labels_matrixA.csv
SPARTACUS10/tests/SPARTACUS_comparison_with_R_function.R
SPARTACUS10/tests/__init__.py
SPARTACUS10/tests/list_neighbors.csv
SPARTACUS10/tests/matrixA.csv
SPARTACUS10/tests/random_data.csv
SPARTACUS10/tests/random_data_spatial.csv
SPARTACUS10/tests/random_labels.csv
SPARTACUS10/tests/test_spartacus.py
SPARTACUS10/tests/test_spatial_silhouette.py
SPARTACUS10-0.0.1.dist-info/AUTHORS.rst
SPARTACUS10-0.0.1.dist-info/LICENSE
SPARTACUS10-0.0.1.dist-info/METADATA
SPARTACUS10-0.0.1.dist-info/WHEEL
SPARTACUS10-0.0.1.dist-info/top_level.txt
SPARTACUS10-0.0.1.dist-info/RECORD
