Metadata-Version: 2.1
Name: SPARTACUS10
Version: 0.0.1
Summary: A package to perform spatial hierarchical agglomerative clustering as well as spatially constrained ensemble clustering. Further includes implementations of the silhouette coefficient, the simplified silhouette coefficient and spatial adaptations thereof.
Home-page: https://github.com/totie10/SPARTACUS
Author: Tobias Tietz
Author-email: tobias.tietz10@gmail.com
License: MIT
Project-URL: Documentation, https://spartacus10.readthedocs.io/
Platform: UNKNOWN
Classifier: Development Status :: 5 - Production/Stable
Classifier: Intended Audience :: Developers
Classifier: License :: OSI Approved :: MIT License
Classifier: Operating System :: Unix
Classifier: Operating System :: POSIX
Classifier: Operating System :: Microsoft :: Windows
Classifier: Programming Language :: Python
Classifier: Programming Language :: Python :: 3
Classifier: Programming Language :: Python :: 3 :: Only
Classifier: Programming Language :: Python :: 3.6
Classifier: Programming Language :: Python :: 3.7
Classifier: Programming Language :: Python :: 3.8
Classifier: Programming Language :: Python :: 3.9
Classifier: Programming Language :: Python :: Implementation :: CPython
Classifier: Programming Language :: Python :: Implementation :: PyPy
Classifier: Topic :: Utilities
Requires-Python: >=3.6
Requires-Dist: numpy (>=1.15.1)
Requires-Dist: scipy (>=1.2.0)
Requires-Dist: scikit-learn (>=0.22.0)
Provides-Extra: dev
Requires-Dist: pytest ; extra == 'dev'
Requires-Dist: pandas (>=0.18.1) ; extra == 'dev'
